uDeepSeek/__init__.py
uDeepSeek/uDeepSeek.py
uLLMpy/__init__.py
uLLMpy/uLLMpy.py
uDeepSeek-0.1.dist-info/LICENSE
uDeepSeek-0.1.dist-info/METADATA
uDeepSeek-0.1.dist-info/WHEEL
uDeepSeek-0.1.dist-info/top_level.txt
uDeepSeek-0.1.dist-info/RECORD
