Metadata-Version: 2.2
Name: uDeepSeek
Version: 0.1
Summary: MicroPython library for LLM access on MCU
Home-page: https://github.com/RiviaRammer/uDeepSeek
Author: RiviaRammer
Author-email: RiviaRammer@gmail.com
Classifier: Programming Language :: Python :: 3
Requires-Python: >=3.7
License-File: LICENSE
Requires-Dist: ujson
Requires-Dist: urequests
Dynamic: author
Dynamic: author-email
Dynamic: classifier
Dynamic: description
Dynamic: description-content-type
Dynamic: home-page
Dynamic: requires-dist
Dynamic: requires-python
Dynamic: summary
